rawutil.py
rawutil-2.8.1.dist-info/LICENSE
rawutil-2.8.1.dist-info/METADATA
rawutil-2.8.1.dist-info/WHEEL
rawutil-2.8.1.dist-info/top_level.txt
rawutil-2.8.1.dist-info/RECORD
