Metadata-Version: 2.1
Name: rawutil
Version: 2.8.1
Summary: A pure-python module to read and write binary data
Home-page: https://github.com/Tyulis/rawutil
Author: Tyulis
Author-email: tyulis@laposte.net
License: MIT
Keywords: structures struct binary bytes formats
Classifier: Development Status :: 4 - Beta
Classifier: Intended Audience :: Developers
Classifier: License :: OSI Approved :: MIT License
Classifier: Programming Language :: Python :: 3 :: Only
Classifier: Programming Language :: Python :: 3.4
Classifier: Programming Language :: Python :: 3.5
Classifier: Programming Language :: Python :: 3.6
Classifier: Programming Language :: Python :: 3.7
Classifier: Programming Language :: Python :: 3.8
Classifier: Programming Language :: Python :: 3.9
Classifier: Programming Language :: Python :: 3.10
Classifier: Topic :: Utilities
Classifier: Operating System :: OS Independent
Requires-Python: >=3.4
License-File: LICENSE
